{
  "_class": "group",
  "booleanOperation": -1,
  "clippingMaskMode": 0,
  "do_objectID": "55E836FE-0798-4DBB-9829-4A1875DF90AB",
  "frame": {
    "_class": "rect",
    "constrainProportions": false,
    "do_objectID": "001F7147-FD6C-40B8-8CD6-9508D39E4CCB",
    "height": 18,
    "width": 18,
    "x": 0,
    "y": 1
  },
  "hasClickThrough": false,
  "hasClippingMask": false,
  "isFixedToViewport": false,
  "isFlippedHorizontal": false,
  "isFlippedVertical": false,
  "isLocked": false,
  "isVisible": true,
  "layerListExpandedType": 2,
  "layers": [
    {
      "class": "shapeGroup",
      "id": "1C2E8337-6636-444A-9F6C-3BA40427A0FA"
    }
  ],
  "name": "baseline-check_box_outline_blank-24px (2)",
  "nameIsFixed": false,
  "resizingConstraint": 63,
  "resizingType": 0,
  "rotation": 0,
  "shouldBreakMaskChain": false,
  "style": {
    "_class": "style",
    "contextSettings": {
      "_class": "graphicsContextSettings",
      "blendMode": 0,
      "do_objectID": "9FA02A96-3CCE-463F-88A0-DD99BFF4F115",
      "opacity": 0.385546875
    },
    "do_objectID": "2BDEB008-FFF4-426C-A2D8-1229AB8C0358",
    "endMarkerType": 0,
    "miterLimit": 10,
    "startMarkerType": 0,
    "windingRule": 1
  },
  "userInfo": {
    "com.animaapp.stc-sketch-plugin": {
      "kModelPropertiesKey": {
      }
    }
  }
}