{
  "_class": "shapePath",
  "booleanOperation": -1,
  "clippingMaskMode": 0,
  "do_objectID": "0C1C06C2-0134-40D4-8961-C074656CA26E",
  "edited": true,
  "frame": {
    "_class": "rect",
    "constrainProportions": false,
    "do_objectID": "A59A0E1D-B41D-49DB-A0AD-DD3AB14E9A95",
    "height": 11,
    "width": 11,
    "x": 1196,
    "y": 372
  },
  "hasClippingMask": false,
  "isClosed": true,
  "isFixedToViewport": false,
  "isFlippedHorizontal": false,
  "isFlippedVertical": false,
  "isLocked": false,
  "isVisible": true,
  "layerListExpandedType": 1,
  "name": "Fill 187",
  "nameIsFixed": false,
  "pointRadiusBehaviour": 1,
  "points": [
    {
      "_class": "curvePoint",
      "cornerRadius": 0,
      "curveFrom": "{0.060019007237372947, 0}",
      "curveMode": 1,
      "curveTo": "{0.060019007237372947, 0}",
      "hasCurveFrom": false,
      "hasCurveTo": false,
      "point": "{0.060019007237372947, 0}"
    },
    {
      "_class": "curvePoint",
      "cornerRadius": 0,
      "curveFrom": "{0.060019007237372947, 0.64707568807339555}",
      "curveMode": 1,
      "curveTo": "{0.060019007237372947, 0.64707568807339555}",
      "hasCurveFrom": false,
      "hasCurveTo": false,
      "point": "{0.060019007237372947, 0.64707568807339555}"
    },
    {
      "_class": "curvePoint",
      "cornerRadius": 0,
      "curveFrom": "{0, 0.96079415137614788}",
      "curveMode": 1,
      "curveTo": "{0, 0.96079415137614788}",
      "hasCurveFrom": false,
      "hasCurveTo": false,
      "point": "{0, 0.96079415137614788}"
    },
    {
      "_class": "curvePoint",
      "cornerRadius": 0,
      "curveFrom": "{0.78002777980846494, 1.0000000000000009}",
      "curveMode": 1,
      "curveTo": "{0.78002777980846494, 1.0000000000000009}",
      "hasCurveFrom": false,
      "hasCurveTo": false,
      "point": "{0.78002777980846494, 1.0000000000000009}"
    },
    {
      "_class": "curvePoint",
      "cornerRadius": 0,
      "curveFrom": "{1, 0.058772935779816085}",
      "curveMode": 1,
      "curveTo": "{1, 0.058772935779816085}",
      "hasCurveFrom": false,
      "hasCurveTo": false,
      "point": "{1, 0.058772935779816085}"
    }
  ],
  "resizingConstraint": 63,
  "resizingType": 0,
  "rotation": 0,
  "shouldBreakMaskChain": false,
  "style": {
    "_class": "style",
    "do_objectID": "9A926D4F-51F3-4641-BBBF-1E1F473AC355",
    "endMarkerType": 0,
    "fills": [
      {
        "_class": "fill",
        "color": {
          "_class": "color",
          "alpha": 1,
          "blue": 0.792,
          "green": 0.776,
          "red": 1
        },
        "fillType": 0,
        "isEnabled": true,
        "noiseIndex": 0,
        "noiseIntensity": 0,
        "patternFillType": 1,
        "patternTileScale": 1
      }
    ],
    "miterLimit": 10,
    "startMarkerType": 0,
    "windingRule": 1
  },
  "userInfo": {
    "com.animaapp.stc-sketch-plugin": {
      "kModelPropertiesKey": {
      }
    }
  }
}