{
  "_class": "shapePath",
  "booleanOperation": -1,
  "clippingMaskMode": 0,
  "do_objectID": "D3DDA9C9-A665-42A9-9890-D14AF7B413DC",
  "edited": true,
  "frame": {
    "_class": "rect",
    "constrainProportions": false,
    "do_objectID": "E3CE6918-0598-418D-8FBD-11164839124D",
    "height": 1,
    "width": 95,
    "x": 964,
    "y": 235
  },
  "hasClippingMask": false,
  "isClosed": true,
  "isFixedToViewport": false,
  "isFlippedHorizontal": false,
  "isFlippedVertical": false,
  "isLocked": false,
  "isVisible": true,
  "layerListExpandedType": 1,
  "name": "Fill 169",
  "nameIsFixed": false,
  "pointRadiusBehaviour": 1,
  "points": [
    {
      "_class": "curvePoint",
      "cornerRadius": 0,
      "curveFrom": "{0, 0.60300000000000864}",
      "curveMode": 1,
      "curveTo": "{0, 0.60300000000000864}",
      "hasCurveFrom": false,
      "hasCurveTo": false,
      "point": "{0, 0.60300000000000864}"
    },
    {
      "_class": "curvePoint",
      "cornerRadius": 0,
      "curveFrom": "{0.99999999999999978, 0.60300000000000864}",
      "curveMode": 1,
      "curveTo": "{0.99999999999999978, 0.60300000000000864}",
      "hasCurveFrom": false,
      "hasCurveTo": false,
      "point": "{0.99999999999999978, 0.60300000000000864}"
    },
    {
      "_class": "curvePoint",
      "cornerRadius": 0,
      "curveFrom": "{0.99999999999999978, 0}",
      "curveMode": 1,
      "curveTo": "{0.99999999999999978, 0}",
      "hasCurveFrom": false,
      "hasCurveTo": false,
      "point": "{0.99999999999999978, 0}"
    },
    {
      "_class": "curvePoint",
      "cornerRadius": 0,
      "curveFrom": "{0, 0}",
      "curveMode": 1,
      "curveTo": "{0, 0}",
      "hasCurveFrom": false,
      "hasCurveTo": false,
      "point": "{0, 0}"
    }
  ],
  "resizingConstraint": 63,
  "resizingType": 0,
  "rotation": 0,
  "shouldBreakMaskChain": false,
  "style": {
    "_class": "style",
    "do_objectID": "CFC626E1-9A9C-4726-A724-03795723E50E",
    "endMarkerType": 0,
    "fills": [
      {
        "_class": "fill",
        "color": {
          "_class": "color",
          "alpha": 1,
          "blue": 1,
          "green": 0.9570000000000001,
          "red": 0.961
        },
        "fillType": 0,
        "isEnabled": true,
        "noiseIndex": 0,
        "noiseIntensity": 0,
        "patternFillType": 1,
        "patternTileScale": 1
      }
    ],
    "miterLimit": 10,
    "startMarkerType": 0,
    "windingRule": 1
  },
  "userInfo": {
    "com.animaapp.stc-sketch-plugin": {
      "kModelPropertiesKey": {
      }
    }
  }
}