{
  "_class": "group",
  "booleanOperation": -1,
  "clippingMaskMode": 0,
  "do_objectID": "8E772B30-BF7C-4730-9042-97461BCCE6F9",
  "frame": {
    "_class": "rect",
    "constrainProportions": false,
    "do_objectID": "21483B33-48F9-466B-95FC-7BDE6FAD307A",
    "height": 44.94336020874021,
    "width": 45.2,
    "x": 0,
    "y": 0
  },
  "hasClickThrough": false,
  "hasClippingMask": false,
  "isFixedToViewport": false,
  "isFlippedHorizontal": false,
  "isFlippedVertical": false,
  "isLocked": false,
  "isVisible": true,
  "layerListExpandedType": 0,
  "layers": [
    {
      "class": "oval",
      "id": "06A214F1-9AE7-45D4-ACAF-60327B26E227"
    },
    {
      "class": "group",
      "id": "B65C5F76-DE3A-4291-A5AB-BCB907309437"
    }
  ],
  "name": "005-google-plus",
  "nameIsFixed": false,
  "resizingConstraint": 63,
  "resizingType": 0,
  "rotation": 0,
  "shouldBreakMaskChain": false,
  "style": {
    "_class": "style",
    "blur": {
      "_class": "blur",
      "center": "{0.5, 0.5}",
      "do_objectID": "F31C1A36-86E3-4FC4-B573-0E935F59BF64",
      "isEnabled": false,
      "motionAngle": 0,
      "radius": 4.000000059604645,
      "saturation": 1,
      "type": 0
    },
    "do_objectID": "7ECC1788-45FB-4D84-AED0-E2A4AE18D16A",
    "endMarkerType": 0,
    "miterLimit": 10,
    "startMarkerType": 0,
    "windingRule": 1
  },
  "userInfo": {
    "com.animaapp.stc-sketch-plugin": {
      "kModelPropertiesKey": {
      }
    }
  }
}