{
  "_class": "shapePath",
  "booleanOperation": -1,
  "clippingMaskMode": 0,
  "do_objectID": "BE36FE3E-9394-4CBA-A1A1-F4F67480BE43",
  "edited": true,
  "frame": {
    "_class": "rect",
    "constrainProportions": false,
    "do_objectID": "3FA28EC9-AD9A-46B8-BE1C-9CC53EBE0D0E",
    "height": 6,
    "width": 18,
    "x": 435,
    "y": 228
  },
  "hasClippingMask": false,
  "isClosed": false,
  "isFixedToViewport": false,
  "isFlippedHorizontal": false,
  "isFlippedVertical": false,
  "isLocked": false,
  "isVisible": true,
  "layerListExpandedType": 1,
  "name": "Stroke 89",
  "nameIsFixed": false,
  "pointRadiusBehaviour": 1,
  "points": [
    {
      "_class": "curvePoint",
      "cornerRadius": 0,
      "curveFrom": "{0.079342620809753461, 0.58568677792041235}",
      "curveMode": 4,
      "curveTo": "{0, 0}",
      "hasCurveFrom": true,
      "hasCurveTo": false,
      "point": "{0, 0}"
    },
    {
      "_class": "curvePoint",
      "cornerRadius": 0,
      "curveFrom": "{0.72692642577274869, 1.0000000000000009}",
      "curveMode": 2,
      "curveTo": "{0.27307357422725193, 1.0000000000000009}",
      "hasCurveFrom": true,
      "hasCurveTo": true,
      "point": "{0.50000000000000033, 1.0000000000000009}"
    },
    {
      "_class": "curvePoint",
      "cornerRadius": 0,
      "curveFrom": "{1.0000000000000007, 0}",
      "curveMode": 4,
      "curveTo": "{0.92054854157597032, 0.58568677792041235}",
      "hasCurveFrom": false,
      "hasCurveTo": true,
      "point": "{1.0000000000000007, 0}"
    }
  ],
  "resizingConstraint": 63,
  "resizingType": 0,
  "rotation": 0,
  "shouldBreakMaskChain": false,
  "style": {
    "_class": "style",
    "borders": [
      {
        "_class": "border",
        "color": {
          "_class": "color",
          "alpha": 1,
          "blue": 1,
          "green": 0.902,
          "red": 0.686
        },
        "fillType": 0,
        "isEnabled": true,
        "position": 0,
        "thickness": 1
      }
    ],
    "do_objectID": "E4A359DB-CF5B-4392-963E-BC9A9D294FDA",
    "endMarkerType": 0,
    "miterLimit": 10,
    "startMarkerType": 0,
    "windingRule": 1
  }
}