{
  "_class": "text",
  "attributedString": {
    "_class": "attributedString",
    "attributes": [
      {
        "_class": "stringAttribute",
        "attributes": {
          "MSAttributedStringColorAttribute": {
            "_class": "color",
            "alpha": 1,
            "blue": 0.6509803922,
            "green": 0.6274509804,
            "red": 0.5960784314
          },
          "MSAttributedStringFontAttribute": {
            "_class": "fontDescriptor",
            "attributes": {
              "name": "VisbyCF-Medium",
              "size": 14
            }
          },
          "kerning": 0,
          "paragraphStyle": {
            "_class": "paragraphStyle",
            "alignment": 0,
            "baseWritingDirection": 0
          }
        },
        "length": 13,
        "location": 0
      }
    ],
    "string": "Profilinə bax"
  },
  "automaticallyDrawOnUnderlyingPath": false,
  "booleanOperation": 0,
  "clippingMaskMode": 0,
  "do_objectID": "63DC585E-BBD8-4F3B-A8C0-8D0DF4780409",
  "dontSynchroniseWithSymbol": false,
  "frame": {
    "_class": "rect",
    "constrainProportions": false,
    "do_objectID": "2F24D3FF-CE2B-4E1F-9FDF-2754D6F5075E",
    "height": 17,
    "width": 80,
    "x": 35,
    "y": 0
  },
  "glyphBounds": "{{0, 4}, {80, 11}}",
  "hasClippingMask": false,
  "isFixedToViewport": false,
  "isFlippedHorizontal": false,
  "isFlippedVertical": false,
  "isLocked": false,
  "isVisible": true,
  "layerListExpandedType": 0,
  "lineSpacingBehaviour": 2,
  "name": "Profilinə bax",
  "nameIsFixed": false,
  "resizingConstraint": 47,
  "resizingType": 0,
  "rotation": 0,
  "shouldBreakMaskChain": false,
  "style": {
    "_class": "style",
    "do_objectID": "F524CF10-A37E-4280-B2B6-CEB24E98BD00",
    "endMarkerType": 0,
    "miterLimit": 10,
    "startMarkerType": 0,
    "textStyle": {
      "_class": "textStyle",
      "do_objectID": "7D9AE9B3-2C95-4319-9640-26439DE87CB5",
      "encodedAttributes": {
        "MSAttributedStringColorAttribute": {
          "_class": "color",
          "alpha": 1,
          "blue": 0.6509803922,
          "green": 0.6274509804,
          "red": 0.5960784314
        },
        "MSAttributedStringFontAttribute": {
          "_class": "fontDescriptor",
          "attributes": {
            "name": "VisbyCF-Medium",
            "size": 14
          }
        },
        "kerning": 0,
        "paragraphStyle": {
          "_class": "paragraphStyle",
          "alignment": 0,
          "baseWritingDirection": 0
        }
      },
      "verticalAlignment": 0
    },
    "windingRule": 1
  },
  "textBehaviour": 0,
  "userInfo": {
    "com.animaapp.stc-sketch-plugin": {
      "kModelPropertiesKey": {
        "isAutoWidth": 1
      }
    }
  }
}