{
  "_class": "shapePath",
  "booleanOperation": -1,
  "clippingMaskMode": 0,
  "do_objectID": "B328309C-2BBF-4436-934C-32E5B9C19EC4",
  "edited": true,
  "frame": {
    "_class": "rect",
    "constrainProportions": false,
    "do_objectID": "ACE3C4FB-9CF3-4146-BEE6-5302E249192F",
    "height": 3.275213734972267,
    "width": 3.305165165165167,
    "x": 16.16205405405406,
    "y": 1.747946853627353
  },
  "hasClippingMask": false,
  "isClosed": false,
  "isFixedToViewport": false,
  "isFlippedHorizontal": false,
  "isFlippedVertical": false,
  "isLocked": false,
  "isVisible": true,
  "layerListExpandedType": 0,
  "name": "Path",
  "nameIsFixed": false,
  "pointRadiusBehaviour": 1,
  "points": [
    {
      "_class": "curvePoint",
      "cornerRadius": 0,
      "curveFrom": "{0.22422997946611947, 1}",
      "curveMode": 4,
      "curveTo": "{0.50020533880903528, 1}",
      "hasCurveFrom": true,
      "hasCurveTo": false,
      "point": "{0.50020533880903528, 1}"
    },
    {
      "_class": "curvePoint",
      "cornerRadius": 0,
      "curveFrom": "{0, 0.22432210353327886}",
      "curveMode": 2,
      "curveTo": "{0, 0.77567789646672114}",
      "hasCurveFrom": true,
      "hasCurveTo": true,
      "point": "{0, 0.50000000000000056}"
    },
    {
      "_class": "curvePoint",
      "cornerRadius": 0,
      "curveFrom": "{0.77577002053388167, 0}",
      "curveMode": 2,
      "curveTo": "{0.22422997946611947, 0}",
      "hasCurveFrom": true,
      "hasCurveTo": true,
      "point": "{0.50020533880903528, 0}"
    },
    {
      "_class": "curvePoint",
      "cornerRadius": 0,
      "curveFrom": "{1, 0.77567789646672114}",
      "curveMode": 2,
      "curveTo": "{1, 0.22432210353327886}",
      "hasCurveFrom": true,
      "hasCurveTo": true,
      "point": "{1, 0.50000000000000056}"
    },
    {
      "_class": "curvePoint",
      "cornerRadius": 0,
      "curveFrom": "{0.50020533880903528, 1}",
      "curveMode": 4,
      "curveTo": "{0.77577002053388167, 1}",
      "hasCurveFrom": false,
      "hasCurveTo": true,
      "point": "{0.50020533880903528, 1}"
    }
  ],
  "resizingConstraint": 63,
  "resizingType": 0,
  "rotation": 0,
  "shouldBreakMaskChain": false,
  "style": {
    "_class": "style",
    "blur": {
      "_class": "blur",
      "center": "{0.5, 0.5}",
      "do_objectID": "4EE0D53F-5202-4B04-8952-5D7DB447DCAA",
      "isEnabled": false,
      "motionAngle": 0,
      "radius": 4.000000059604645,
      "saturation": 1,
      "type": 0
    },
    "do_objectID": "3F5D186C-0390-44C8-9BAF-167A3754C01F",
    "endMarkerType": 0,
    "fills": [
      {
        "_class": "fill",
        "color": {
          "_class": "color",
          "alpha": 1,
          "blue": 0.737,
          "green": 0.361,
          "red": 0.439
        },
        "fillType": 1,
        "gradient": {
          "_class": "gradient",
          "elipseLength": 0,
          "from": "{1.0798462849698749, 1.4208401534841524}",
          "gradientType": 0,
          "stops": [
            {
              "_class": "gradientStop",
              "color": {
                "_class": "color",
                "alpha": 1,
                "blue": 0.5176470588235295,
                "green": 0.8431372549019609,
                "red": 0.9803921568627451
              },
              "position": 0
            },
            {
              "_class": "gradientStop",
              "color": {
                "_class": "color",
                "alpha": 1,
                "blue": 0.2588235294117647,
                "green": 0.5137254901960784,
                "red": 0.9294117647058824
              },
              "position": 0.289784845548148
            },
            {
              "_class": "gradientStop",
              "color": {
                "_class": "color",
                "alpha": 1,
                "blue": 0.4705882352941178,
                "green": 0.2666666666666667,
                "red": 0.7803921568627451
              },
              "position": 0.5790137102412246
            },
            {
              "_class": "gradientStop",
              "color": {
                "_class": "color",
                "alpha": 1,
                "blue": 0.7294117647058823,
                "green": 0.2901960784313726,
                "red": 0.5411764705882351
              },
              "position": 0.7832537935866024
            },
            {
              "_class": "gradientStop",
              "color": {
                "_class": "color",
                "alpha": 1,
                "blue": 0.807843137254902,
                "green": 0.4039215686274512,
                "red": 0.2980392156862746
              },
              "position": 1
            }
          ],
          "to": "{0, -0.55565470652784299}"
        },
        "isEnabled": true,
        "noiseIndex": 0,
        "noiseIntensity": 0,
        "patternFillType": 1,
        "patternTileScale": 1
      }
    ],
    "miterLimit": 10,
    "startMarkerType": 0,
    "windingRule": 1
  },
  "userInfo": {
    "com.animaapp.stc-sketch-plugin": {
      "kModelPropertiesKey": {
      }
    }
  }
}