{
  "_class": "group",
  "booleanOperation": -1,
  "clippingMaskMode": 0,
  "do_objectID": "70403B58-100D-49DC-8F4C-FCC9AF2E94B3",
  "frame": {
    "_class": "rect",
    "constrainProportions": false,
    "do_objectID": "43B7322B-A48E-4880-AFBE-68F4C0B83633",
    "height": 49.28000022888182,
    "width": 1238,
    "x": 180,
    "y": 15
  },
  "hasClickThrough": false,
  "hasClippingMask": false,
  "isFixedToViewport": false,
  "isFlippedHorizontal": false,
  "isFlippedVertical": false,
  "isLocked": false,
  "isVisible": true,
  "layerListExpandedType": 0,
  "layers": [
    {
      "class": "group",
      "id": "E3AEB0D6-DF24-49C6-8058-B6E606ABB77F"
    },
    {
      "class": "text",
      "id": "B36066CB-454A-4B1C-B602-696FDB8221EC"
    },
    {
      "class": "text",
      "id": "D00F81D6-5C22-41E8-9BD5-4D36C2B86CC0"
    }
  ],
  "name": "Group 3",
  "nameIsFixed": false,
  "resizingConstraint": 63,
  "resizingType": 0,
  "rotation": 0,
  "shouldBreakMaskChain": false,
  "style": {
    "_class": "style",
    "do_objectID": "E4A5696E-1823-4BD2-85EA-009CB9491627",
    "endMarkerType": 0,
    "miterLimit": 10,
    "startMarkerType": 0,
    "windingRule": 1
  },
  "userInfo": {
    "com.animaapp.stc-sketch-plugin": {
      "kModelPropertiesKey": {
      }
    }
  }
}